tart/__init__.py
tart/cli/__init__.py
tart/cli/cli.py
tart/data/.gitignore
tart/data/example/embed/raw/example_0.json
tart/data/example/embed/raw/example_1.json
tart/data/example/embed/raw/example_2.json
tart/data/example/embed/raw/example_3.json
tart/data/example/test/raw/g1.json
tart/data/example/test/raw/g2.json
tart/data/example/train/raw/g1.json
tart/data/example/train/raw/g2.json
tart/example/__init__.py
tart/example/learn.py
tart/example/predict.py
tart/example/tart-config.json
tart/inference/__init__.py
tart/inference/embed.py
tart/inference/predict.py
tart/representation/__init__.py
tart/representation/config.py
tart/representation/dataset.py
tart/representation/encoders.py
tart/representation/models.py
tart/representation/test.py
tart/representation/train.py
tart/utils/__init__.py
tart/utils/config_utils.py
tart/utils/graph_utils.py
tart/utils/infer_utils.py
tart/utils/model_utils.py
tart/utils/tart_utils.py
tart/utils/train_utils.py
tart_lib-0.1.1.dist-info/LICENSE
tart_lib-0.1.1.dist-info/METADATA
tart_lib-0.1.1.dist-info/WHEEL
tart_lib-0.1.1.dist-info/entry_points.txt
tart_lib-0.1.1.dist-info/RECORD
